searxng_simple_mcp/__init__.py
searxng_simple_mcp/config.py
searxng_simple_mcp/searxng_client.py
searxng_simple_mcp/server.py
searxng_simple_mcp-1.0.3.dist-info/entry_points.txt
searxng_simple_mcp-1.0.3.dist-info/licenses/LICENSE
searxng_simple_mcp-1.0.3.dist-info/WHEEL
searxng_simple_mcp-1.0.3.dist-info/METADATA
searxng_simple_mcp-1.0.3.dist-info/RECORD
