Metadata-Version: 2.4
Name: searxng-simple-mcp
Version: 1.0.3
Summary: SearxNG MCP Server
Author: Dmitriy Safonov
Requires-Python: >=3.10
License-Expression: MIT
License-File: LICENSE
Requires-Dist: fastmcp
Requires-Dist: httpx
Requires-Dist: mcp[cli]>=1.6.0
Requires-Dist: pydantic
Requires-Dist: pydantic-settings
